{
  "$schema": "https://schema.tauri.app/config/2",
  "productName": "Syncology",
  "version": "0.1.99",
  "identifier": "com.pusync.app",
  "build": {
    "beforeDevCommand": "npm run dev",
    "devUrl": "http://localhost:1420",
    "beforeBuildCommand": "npm run build",
    "frontendDist": "../dist"
  },
  "app": {
    "windows": [
      {
        "title": "Syncology",
        "width": 800,
        "height": 600
      }
    ],
    "security": {
      "csp": null
    }
  },
  "bundle": {
    "active": true,
    "targets": "all",
    "createUpdaterArtifacts": true,
    "icon": [
      "icons/32x32.png",
      "icons/128x128.png",
      "icons/128x128@2x.png",
      "icons/icon.icns",
      "icons/icon.ico"
    ]
  },
  "plugins": {
    "updater": {
      "pubkey": "dW50cnVzdGVkIGNvbW1lbnQ6IG1pbmlzaWduIHB1YmxpYyBrZXk6IDY2NEU0NERDMzBGMjc3QTYKUldTbWQvSXczRVJPWm5GMmNMZ0RPWnhwQ3lQZ280d2tkZVo2UTREa1A2enpCZDVLaksybnllejAK",
      "endpoints": [
        "https://github.com/alertxsto/syncology-rust/releases/download/nightly/latest.json",
        "https://github.com/alertxsto/syncology-rust/releases/latest/download/latest.json"
      ]
    }
  }
}
